<?xml version="1.0" encoding="utf-8"?>
<doublecmd DCVersion="0.6.3 beta" ConfigVersion="7">
  <Configuration Save="True" SortOrder="0">
    <UseConfigInProgramDir>False</UseConfigInProgramDir>
  </Configuration>
  <Colors>
    <FileFilters>
      <Filter>
        <Name>Pascal sources</Name>
        <FileMasks>*.pas;*.pp</FileMasks>
        <Color>32768</Color>
        <Attributes/>
      </Filter>
      <Filter>
        <Name>Pascal binaries</Name>
        <FileMasks>*.ppu;*.o;*.dcu</FileMasks>
        <Color>16711680</Color>
        <Attributes/>
      </Filter>
      <Filter>
        <Name>Specified Executables</Name>
        <FileMasks>*</FileMasks>
        <Color>55758</Color>
        <Attributes>-rwxrwxr*x</Attributes>
      </Filter>
      <Filter>
        <Name>Executables</Name>
        <FileMasks>*</FileMasks>
        <Color>32768</Color>
        <Attributes>-*x*</Attributes>
      </Filter>
    </FileFilters>
    <Foreground>-2147483640</Foreground>
    <Background>-2147483643</Background>
    <Background2>-2147483643</Background2>
    <Mark>255</Mark>
    <Cursor>-2147483635</Cursor>
    <CursorText>-2147483634</CursorText>
    <UseInvertedSelection>False</UseInvertedSelection>
    <InactivePanelBrightness>100</InactivePanelBrightness>
    <UseFrameCursor>False</UseFrameCursor>
    <FreeSpaceIndicator>
      <ForeColor>0</ForeColor>
      <BackColor>16777215</BackColor>
      <UseGradient>True</UseGradient>
    </FreeSpaceIndicator>
  </Colors>
  <Plugins>
    <DsxPlugins/>
    <WcxPlugins>
      <WcxPlugin Enabled="True">
        <ArchiveExt>zip</ArchiveExt>
        <Path>%commander_path%/plugins/wcx/zip/zip.wcx</Path>
        <Flags>607</Flags>
      </WcxPlugin>
      <WcxPlugin Enabled="True">
        <ArchiveExt>tar</ArchiveExt>
        <Path>%commander_path%/plugins/wcx/zip/zip.wcx</Path>
        <Flags>95</Flags>
      </WcxPlugin>
      <WcxPlugin Enabled="True">
        <ArchiveExt>bz2</ArchiveExt>
        <Path>%commander_path%/plugins/wcx/zip/zip.wcx</Path>
        <Flags>91</Flags>
      </WcxPlugin>
      <WcxPlugin Enabled="True">
        <ArchiveExt>tbz</ArchiveExt>
        <Path>%commander_path%/plugins/wcx/zip/zip.wcx</Path>
        <Flags>95</Flags>
      </WcxPlugin>
      <WcxPlugin Enabled="True">
        <ArchiveExt>gz</ArchiveExt>
        <Path>%commander_path%/plugins/wcx/zip/zip.wcx</Path>
        <Flags>91</Flags>
      </WcxPlugin>
      <WcxPlugin Enabled="True">
        <ArchiveExt>tgz</ArchiveExt>
        <Path>%commander_path%/plugins/wcx/zip/zip.wcx</Path>
        <Flags>95</Flags>
      </WcxPlugin>
      <WcxPlugin Enabled="True">
        <ArchiveExt>lzma</ArchiveExt>
        <Path>%commander_path%/plugins/wcx/zip/zip.wcx</Path>
        <Flags>1</Flags>
      </WcxPlugin>
      <WcxPlugin Enabled="True">
        <ArchiveExt>tlz</ArchiveExt>
        <Path>%commander_path%/plugins/wcx/zip/zip.wcx</Path>
        <Flags>95</Flags>
      </WcxPlugin>
      <WcxPlugin Enabled="True">
        <ArchiveExt>xz</ArchiveExt>
        <Path>%commander_path%/plugins/wcx/zip/zip.wcx</Path>
        <Flags>91</Flags>
      </WcxPlugin>
      <WcxPlugin Enabled="True">
        <ArchiveExt>txz</ArchiveExt>
        <Path>%commander_path%/plugins/wcx/zip/zip.wcx</Path>
        <Flags>95</Flags>
      </WcxPlugin>
      <WcxPlugin Enabled="True">
        <ArchiveExt>zipx</ArchiveExt>
        <Path>%commander_path%/plugins/wcx/zip/zip.wcx</Path>
        <Flags>84</Flags>
      </WcxPlugin>
      <WcxPlugin Enabled="True">
        <ArchiveExt>cpio</ArchiveExt>
        <Path>%commander_path%/plugins/wcx/cpio/cpio.wcx</Path>
        <Flags>4</Flags>
      </WcxPlugin>
      <WcxPlugin Enabled="True">
        <ArchiveExt>deb</ArchiveExt>
        <Path>%commander_path%/plugins/wcx/deb/deb.wcx</Path>
        <Flags>4</Flags>
      </WcxPlugin>
      <WcxPlugin Enabled="True">
        <ArchiveExt>rpm</ArchiveExt>
        <Path>%commander_path%/plugins/wcx/rpm/rpm.wcx</Path>
        <Flags>4</Flags>
      </WcxPlugin>
      <WcxPlugin Enabled="True">
        <ArchiveExt>rar</ArchiveExt>
        <Path>%commander_path%/plugins/wcx/unrar/unrar.wcx</Path>
        <Flags>68</Flags>
      </WcxPlugin>
    </WcxPlugins>
    <WdxPlugins>
      <WdxPlugin>
        <Name>rpm_wdx</Name>
        <Path>%COMMANDER_PATH%/plugins/wdx/rpm_wdx/rpm_wdx.wdx</Path>
        <DetectString>EXT="RPM"</DetectString>
      </WdxPlugin>
      <WdxPlugin>
        <Name>deb_wdx</Name>
        <Path>%COMMANDER_PATH%/plugins/wdx/deb_wdx/deb_wdx.wdx</Path>
        <DetectString>EXT="DEB"</DetectString>
      </WdxPlugin>
    </WdxPlugins>
    <WfxPlugins>
      <WfxPlugin Enabled="True">
        <Name>FTP</Name>
        <Path>%commander_path%/plugins/wfx/ftp/ftp.wfx</Path>
      </WfxPlugin>
      <WfxPlugin Enabled="True">
        <Name>Windows Network</Name>
        <Path>%commander_path%/plugins/wfx/samba/samba.wfx</Path>
      </WfxPlugin>
    </WfxPlugins>
    <WlxPlugins>
      <WlxPlugin Enabled="True">
        <Name>wlxMplayer</Name>
        <Path>%COMMANDER_PATH%/plugins/wlx/wlxmplayer/wlxmplayer.wlx</Path>
        <DetectString>(EXT="MPG")|(EXT="AVI")|(EXT="MPEG")|(EXT="FLV")</DetectString>
      </WlxPlugin>
    </WlxPlugins>
  </Plugins>
  <Toolbars>
    <MainToolbar>
      <Row>
        <Command>
          <ID>{2F0498B2-EBC9-48EB-9B53-3ACD96B8B437}</ID>
          <Icon>cm_refresh</Icon>
          <Command>cm_Refresh</Command>
        </Command>
        <Command>
          <ID>{3D6FB9AE-182C-484E-AEED-B2C6E145F46F}</ID>
          <Icon>cm_runterm</Icon>
          <Command>cm_RunTerm</Command>
        </Command>
        <Command>
          <ID>{8DE7C695-7FFC-49D3-8918-66CF2A607292}</ID>
          <Icon>cm_options</Icon>
          <Command>cm_Options</Command>
        </Command>
        <Separator/>
        <Command>
          <ID>{33920532-931F-4A57-8A4F-B319C6C8C7F3}</ID>
          <Icon>cm_briefview</Icon>
          <Command>cm_BriefView</Command>
        </Command>
        <Command>
          <ID>{8AB6C120-8C97-4BF0-B150-73335DEC5397}</ID>
          <Icon>cm_columnsview</Icon>
          <Command>cm_ColumnsView</Command>
        </Command>
        <Command>
          <ID>{924F1E43-BB91-4380-A5FE-06EC257FF3C8}</ID>
          <Icon>cm_thumbnailsview</Icon>
          <Command>cm_ThumbnailsView</Command>
        </Command>
        <Separator/>
        <Command>
          <ID>{356D7DA2-3C0C-4D0D-8336-4B076B0ACDA5}</ID>
          <Icon>cm_flatview</Icon>
          <Command>cm_FlatView</Command>
        </Command>
        <Separator/>
        <Command>
          <ID>{4139871E-40F7-426D-9EB9-CAC7F350D9B7}</ID>
          <Icon>cm_viewhistoryprev</Icon>
          <Command>cm_ViewHistoryPrev</Command>
        </Command>
        <Command>
          <ID>{C62E5EE2-F3B7-4C25-B490-33F20E739D7E}</ID>
          <Icon>cm_viewhistorynext</Icon>
          <Command>cm_ViewHistoryNext</Command>
        </Command>
        <Separator/>
        <Command>
          <ID>{DEF930BE-02CB-45EA-8C08-A019AF1FE583}</ID>
          <Icon>cm_markplus</Icon>
          <Command>cm_MarkPlus</Command>
        </Command>
        <Command>
          <ID>{F43CC745-2C69-4311-BD4F-837F63C2707C}</ID>
          <Icon>cm_markminus</Icon>
          <Command>cm_MarkMinus</Command>
        </Command>
        <Command>
          <ID>{9107CD4A-03E7-4A85-AECE-2875BC9238CE}</ID>
          <Icon>cm_markinvert</Icon>
          <Command>cm_MarkInvert</Command>
        </Command>
        <Separator/>
        <Command>
          <ID>{68AAF600-A0F0-4629-8634-46C4347BF12A}</ID>
          <Icon>cm_packfiles</Icon>
          <Command>cm_PackFiles</Command>
        </Command>
        <Command>
          <ID>{612B5103-58FF-42F3-AA69-0B831EBDC04F}</ID>
          <Icon>cm_extractfiles</Icon>
          <Command>cm_ExtractFiles</Command>
        </Command>
        <Separator/>
        <Command>
          <ID>{28BC4A48-09EE-401E-9E5A-41E747B0E252}</ID>
          <Icon>cm_search</Icon>
          <Command>cm_Search</Command>
        </Command>
        <Command>
          <ID>{B9332387-E3F1-410B-9B16-FA981FDD1A4B}</ID>
          <Icon>cm_multirename</Icon>
          <Command>cm_MultiRename</Command>
        </Command>
        <Command>
          <ID>{B040AC82-E4E6-4372-BC25-6458F94F96EF}</ID>
          <Icon>cm_syncdirs</Icon>
          <Command>cm_SyncDirs</Command>
        </Command>
        <Command>
          <ID>{A6F990BA-D8ED-47FB-8113-65FE51692423}</ID>
          <Icon>cm_copyfullnamestoclip</Icon>
          <Command>cm_CopyFullNamesToClip</Command>
        </Command>
      </Row>
    </MainToolbar>
  </Toolbars>
  <Language>
    <POFileName>doublecmd.ca.po</POFileName>
  </Language>
  <Behaviours>
    <GoToRoot>False</GoToRoot>
    <RunInTerminal>xterm -e sh -c</RunInTerminal>
    <RunTerminal>xterm</RunTerminal>
    <OnlyOneAppInstance>False</OnlyOneAppInstance>
    <LynxLike>True</LynxLike>
    <FileSizeFormat>0</FileSizeFormat>
    <MinimizeToTray>False</MinimizeToTray>
    <AlwaysShowTrayIcon>False</AlwaysShowTrayIcon>
    <Mouse>
      <Selection Enabled="True">
        <Button>0</Button>
      </Selection>
      <ScrollMode>1</ScrollMode>
      <WheelScrollLines>3</WheelScrollLines>
    </Mouse>
    <AutoFillColumns>False</AutoFillColumns>
    <AutoSizeColumn>1</AutoSizeColumn>
    <BriefViewFileExtAligned>False</BriefViewFileExtAligned>
    <DateTimeFormat>dd/mm/yy</DateTimeFormat>
    <CutTextToColumnWidth>True</CutTextToColumnWidth>
    <ShowSystemFiles>False</ShowSystemFiles>
    <ListFilesInThread>True</ListFilesInThread>
    <LoadIconsSeparately>True</LoadIconsSeparately>
    <DelayLoadingTabs>True</DelayLoadingTabs>
    <HighlightUpdatedFiles>True</HighlightUpdatedFiles>
    <DriveBlackList/>
    <DriveBlackListUnmounted>False</DriveBlackListUnmounted>
  </Behaviours>
  <Tools>
    <Viewer Enabled="False">
      <Path/>
      <Parameters/>
      <RunInTerminal>False</RunInTerminal>
      <KeepTerminalOpen>False</KeepTerminalOpen>
    </Viewer>
    <Editor Enabled="False">
      <Path/>
      <Parameters/>
      <RunInTerminal>False</RunInTerminal>
      <KeepTerminalOpen>False</KeepTerminalOpen>
    </Editor>
    <Differ Enabled="False">
      <Path/>
      <Parameters/>
      <RunInTerminal>False</RunInTerminal>
      <KeepTerminalOpen>False</KeepTerminalOpen>
      <FramePosAfterComp>0</FramePosAfterComp>
    </Differ>
  </Tools>
  <Fonts>
    <Main>
      <Name>default</Name>
      <Size>10</Size>
      <Style>1</Style>
    </Main>
    <Editor>
      <Name>Monospace</Name>
      <Size>14</Size>
      <Style>0</Style>
    </Editor>
    <Viewer>
      <Name>Monospace</Name>
      <Size>14</Size>
      <Style>0</Style>
    </Viewer>
    <Log>
      <Name>Monospace</Name>
      <Size>12</Size>
      <Style>0</Style>
    </Log>
    <ViewerBook>
      <Name>default</Name>
      <Size>16</Size>
      <Style>1</Style>
    </ViewerBook>
  </Fonts>
  <ToolTips>
    <ShowToolTipMode>1</ShowToolTipMode>
    <CustomFields/>
  </ToolTips>
  <Layout>
    <MainMenu>True</MainMenu>
    <ButtonBar Enabled="True">
      <FlatIcons>True</FlatIcons>
      <ButtonHeight>24</ButtonHeight>
      <IconSize>16</IconSize>
      <ReportErrorWithCommands>False</ReportErrorWithCommands>
    </ButtonBar>
    <DriveBar1>True</DriveBar1>
    <DriveBar2>True</DriveBar2>
    <DriveBarFlat>True</DriveBarFlat>
    <DrivesListButton Enabled="True">
      <ShowLabel>True</ShowLabel>
      <ShowFileSystem>True</ShowFileSystem>
      <ShowFreeSpace>True</ShowFreeSpace>
    </DrivesListButton>
    <DirectoryTabs>True</DirectoryTabs>
    <CurrentDirectory>True</CurrentDirectory>
    <TabHeader>True</TabHeader>
    <StatusBar>True</StatusBar>
    <CmdLine>True</CmdLine>
    <LogWindow>False</LogWindow>
    <TermWindow>False</TermWindow>
    <KeyButtons>True</KeyButtons>
    <InterfaceFlat>True</InterfaceFlat>
    <DriveFreeSpace>True</DriveFreeSpace>
    <DriveIndicator>False</DriveIndicator>
    <ProgressInMenuBar>False</ProgressInMenuBar>
    <PanelOfOperationsInBackground>True</PanelOfOperationsInBackground>
    <HorizontalFilePanels>False</HorizontalFilePanels>
    <ShortFormatDriveInfo>True</ShortFormatDriveInfo>
  </Layout>
  <FilesViews>
    <Sorting>
      <CaseSensitivity>0</CaseSensitivity>
      <NaturalSorting>False</NaturalSorting>
      <SortFolderMode>0</SortFolderMode>
      <NewFilesPosition>2</NewFilesPosition>
      <UpdatedFilesPosition>2</UpdatedFilesPosition>
    </Sorting>
  </FilesViews>
  <Keyboard>
    <Typing>
      <Actions>
        <NoModifier>2</NoModifier>
        <Alt>0</Alt>
        <CtrlAlt>3</CtrlAlt>
      </Actions>
    </Typing>
  </Keyboard>
  <FileOperations>
    <BufferSize>524288</BufferSize>
    <UseMmapInSearch>False</UseMmapInSearch>
    <PartialNameSearch>True</PartialNameSearch>
    <WipePassNumber>1</WipePassNumber>
    <DropReadOnlyFlag>False</DropReadOnlyFlag>
    <ProcessComments>False</ProcessComments>
    <RenameSelOnlyName>True</RenameSelOnlyName>
    <ShowCopyTabSelectPanel>False</ShowCopyTabSelectPanel>
    <UseTrash>True</UseTrash>
    <SkipFileOpError>False</SkipFileOpError>
    <TypeOfDuplicatedRename>0</TypeOfDuplicatedRename>
    <ShowDialogOnDragDrop>False</ShowDialogOnDragDrop>
    <DragAndDropTextRichtextDesireLevel>0</DragAndDropTextRichtextDesireLevel>
    <DragAndDropTextHtmlDesireLevel>1</DragAndDropTextHtmlDesireLevel>
    <DragAndDropTextUnicodeDesireLevel>2</DragAndDropTextUnicodeDesireLevel>
    <DragAndDropTextSimpletextDesireLevel>3</DragAndDropTextSimpletextDesireLevel>
    <DragAndDropAskFormatEachTime>False</DragAndDropAskFormatEachTime>
    <DragAndDropTextAutoFilename>False</DragAndDropTextAutoFilename>
    <DragAndDropSaveUnicodeTextInUFT8>True</DragAndDropSaveUnicodeTextInUFT8>
    <OverwriteFolder>False</OverwriteFolder>
    <NtfsHourTimeDelay>False</NtfsHourTimeDelay>
    <ProgressKind>0</ProgressKind>
    <Confirmations>15</Confirmations>
    <Options>
      <Symlink>0</Symlink>
      <CorrectLinks>False</CorrectLinks>
      <FileExists>0</FileExists>
      <DirectoryExists>0</DirectoryExists>
      <SetPropertyError>0</SetPropertyError>
      <ReserveSpace>False</ReserveSpace>
      <CheckFreeSpace>True</CheckFreeSpace>
      <CopyAttributes>True</CopyAttributes>
      <CopyTime>True</CopyTime>
      <CopyOwnership>True</CopyOwnership>
    </Options>
  </FileOperations>
  <Tabs>
    <Options>1809</Options>
    <CharacterLimit>32</CharacterLimit>
    <Position>0</Position>
    <OpenedTabs>
      <Left>
        <ActiveTab>0</ActiveTab>
        <Tab>
          <FileView Type="columns">
            <History>
              <Entry Active="True">
                <FileSource Type="FileSystem"/>
                <Paths>
                  <Path Filename="Dropbox">/home/xquang/</Path>
                  <Path Filename="photo">/home/xquang/Dropbox/</Path>
                  <Path Filename="delta">/home/xquang/Dropbox/photo/</Path>
                  <Path Filename="..">/home/xquang/Dropbox/photo/delta/</Path>
                  <Path Filename="..">/home/xquang/Dropbox/photo/</Path>
                  <Path Filename="..">/home/xquang/Dropbox/</Path>
                  <Path Filename="..">/home/xquang/</Path>
                  <Path Filename="..">/home/</Path>
                  <Path Filename="mnt">/</Path>
                  <Path Filename="..">/mnt/</Path>
                  <Path Filename="home">/</Path>
                  <Path Filename="xquang">/home/</Path>
                  <Path Filename="relax">/home/xquang/</Path>
                  <Path Filename="photo">/home/xquang/relax/</Path>
                  <Path Filename="1">/home/xquang/relax/photo/</Path>
                  <Path Filename="DSC_1116.JPG">/home/xquang/relax/photo/1/</Path>
                  <Path Filename="..">/home/xquang/Dropbox/photo/Gem/</Path>
                  <Path Filename="..">/home/xquang/Dropbox/photo/</Path>
                  <Path Filename="..">/home/xquang/Dropbox/</Path>
                  <Path Filename="Downloads">/home/xquang/</Path>
                  <Path Filename="Billing_Management_Console.png">/home/xquang/Downloads/</Path>
                </Paths>
              </Entry>
            </History>
            <ColumnsView>
              <ColumnsSet>Default</ColumnsSet>
            </ColumnsView>
          </FileView>
        </Tab>
      </Left>
      <Right>
        <ActiveTab>0</ActiveTab>
        <Tab>
          <FileView Type="columns">
            <History>
              <Entry Active="True">
                <FileSource Type="FileSystem"/>
                <Paths>
                  <Path Filename="bin">/home/xquang/</Path>
                  <Path Filename="..">/home/xquang/bin/</Path>
                  <Path Filename="Calvin">/home/xquang/</Path>
                  <Path Filename="..">/home/xquang/Calvin/</Path>
                  <Path Filename="eSale">/home/xquang/</Path>
                  <Path Filename="..">/home/xquang/eSale/</Path>
                  <Path Filename="relax">/home/xquang/</Path>
                  <Path Filename="VNG">/home/xquang/relax/</Path>
                  <Path Filename="..">/home/xquang/relax/VNG/</Path>
                  <Path Filename="..">/home/xquang/relax/</Path>
                  <Path Filename="Dropbox">/home/xquang/</Path>
                  <Path Filename="photo">/home/xquang/Dropbox/</Path>
                  <Path Filename="Gem">/home/xquang/Dropbox/photo/</Path>
                  <Path Filename="..">/home/xquang/Dropbox/photo/Gem/</Path>
                </Paths>
              </Entry>
            </History>
            <ColumnsView>
              <ColumnsSet>Default</ColumnsSet>
            </ColumnsView>
          </FileView>
        </Tab>
      </Right>
    </OpenedTabs>
  </Tabs>
  <Log Enabled="True" LogFileWithDateInName="True">
    <FileName>/home/xquang/.config/doublecmd/doublecmd.log</FileName>
    <Options>511</Options>
  </Log>
  <History>
    <SearchReplaceHistory Save="True"/>
    <DirHistory Save="True"/>
    <CmdLineHistory Save="True"/>
    <FileMaskHistory Save="True"/>
  </History>
  <QuickSearch>
    <MatchBeginning>True</MatchBeginning>
    <MatchEnding>True</MatchEnding>
    <Case>1</Case>
    <Items>2</Items>
  </QuickSearch>
  <QuickFilter>
    <AutoHide>True</AutoHide>
  </QuickFilter>
  <Miscellaneous>
    <GridVertLine>False</GridVertLine>
    <GridHorzLine>False</GridHorzLine>
    <ShowWarningMessages>True</ShowWarningMessages>
    <SpaceMovesDown>False</SpaceMovesDown>
    <DirBrackets>True</DirBrackets>
    <InplaceRename>False</InplaceRename>
    <HotDirAddTargetOrNot>False</HotDirAddTargetOrNot>
    <HotDirFullExpandOrNot>False</HotDirFullExpandOrNot>
    <ShowPathInPopup>False</ShowPathInPopup>
    <ShowOnlyValidEnv>True</ShowOnlyValidEnv>
    <WhereToAddNewHotDir>2</WhereToAddNewHotDir>
  </Miscellaneous>
  <Thumbnails Save="True">
    <Width>128</Width>
    <Height>128</Height>
  </Thumbnails>
  <AutoRefresh>
    <Options>3</Options>
    <ExcludeDirs/>
    <Mode>0</Mode>
  </AutoRefresh>
  <Icons>
    <ShowMode>3</ShowMode>
    <ShowOverlays>False</ShowOverlays>
    <Size>16</Size>
    <Exclude>False</Exclude>
    <ExcludeDirs/>
    <CustomDriveIcons>False</CustomDriveIcons>
    <ShowInMenus Enabled="False">
      <Size>16</Size>
    </ShowInMenus>
  </Icons>
  <IgnoreList Enabled="False">
    <IgnoreListFile>/home/xquang/.config/doublecmd/ignorelist.txt</IgnoreListFile>
  </IgnoreList>
  <DirectoryHotList/>
  <Viewer>
    <PreviewVisible>False</PreviewVisible>
    <ImageStretch>False</ImageStretch>
    <CopyMovePath1/>
    <CopyMovePath2/>
    <CopyMovePath3/>
    <CopyMovePath4/>
    <CopyMovePath5/>
    <PaintMode>Pen</PaintMode>
    <PaintWidth>5</PaintWidth>
    <NumberOfColumns>1</NumberOfColumns>
    <ViewerMode>0</ViewerMode>
    <PaintColor>255</PaintColor>
    <BackgroundColor>0</BackgroundColor>
    <FontColor>16777215</FontColor>
    <TextPosition>0</TextPosition>
  </Viewer>
  <SyncDirs>
    <Subdirs>False</Subdirs>
    <ByContent>False</ByContent>
    <IgnoreDate>False</IgnoreDate>
    <FilterCopyRight>True</FilterCopyRight>
    <FilterEqual>True</FilterEqual>
    <FilterNotEqual>True</FilterNotEqual>
    <FilterCopyLeft>True</FilterCopyLeft>
    <FilterDuplicates>True</FilterDuplicates>
    <FilterSingles>True</FilterSingles>
    <FileMask>*</FileMask>
  </SyncDirs>
  <Lua>
    <PathToLibrary>liblua5.1.so.0</PathToLibrary>
  </Lua>
  <NameShortcutFile>shortcuts.scf</NameShortcutFile>
  <LastUsedPacker>zip</LastUsedPacker>
  <UseShellForFileOperations>False</UseShellForFileOperations>
  <SearchTemplates/>
  <ColumnsSets>
    <ColumnsSet>
      <Name>Default</Name>
      <CustomView>False</CustomView>
      <CursorBorder Enabled="False">
        <Color>0</Color>
      </CursorBorder>
      <Columns>
        <Column>
          <Title>Name</Title>
          <FuncString>[DC().GETFILENAMENOEXT{}]</FuncString>
          <Width>250</Width>
          <Align>0</Align>
          <Font>
            <Name>default</Name>
            <Size>10</Size>
            <Style>1</Style>
          </Font>
          <Overcolor>True</Overcolor>
          <TextColor>-2147483640</TextColor>
          <Background>-2147483643</Background>
          <Background2>-2147483643</Background2>
          <MarkColor>255</MarkColor>
          <CursorColor>-2147483635</CursorColor>
          <CursorText>-2147483634</CursorText>
        </Column>
        <Column>
          <Title>Ext</Title>
          <FuncString>[DC().GETFILEEXT{}]</FuncString>
          <Width>50</Width>
          <Align>0</Align>
          <Font>
            <Name>default</Name>
            <Size>10</Size>
            <Style>1</Style>
          </Font>
          <Overcolor>True</Overcolor>
          <TextColor>-2147483640</TextColor>
          <Background>-2147483643</Background>
          <Background2>-2147483643</Background2>
          <MarkColor>255</MarkColor>
          <CursorColor>-2147483635</CursorColor>
          <CursorText>-2147483634</CursorText>
        </Column>
        <Column>
          <Title>Size</Title>
          <FuncString>[DC().GETFILESIZE{}]</FuncString>
          <Width>70</Width>
          <Align>1</Align>
          <Font>
            <Name>default</Name>
            <Size>10</Size>
            <Style>1</Style>
          </Font>
          <Overcolor>True</Overcolor>
          <TextColor>-2147483640</TextColor>
          <Background>-2147483643</Background>
          <Background2>-2147483643</Background2>
          <MarkColor>255</MarkColor>
          <CursorColor>-2147483635</CursorColor>
          <CursorText>-2147483634</CursorText>
        </Column>
        <Column>
          <Title>Date</Title>
          <FuncString>[DC().GETFILETIME{}]</FuncString>
          <Width>70</Width>
          <Align>1</Align>
          <Font>
            <Name>default</Name>
            <Size>10</Size>
            <Style>1</Style>
          </Font>
          <Overcolor>True</Overcolor>
          <TextColor>-2147483640</TextColor>
          <Background>-2147483643</Background>
          <Background2>-2147483643</Background2>
          <MarkColor>255</MarkColor>
          <CursorColor>-2147483635</CursorColor>
          <CursorText>-2147483634</CursorText>
        </Column>
        <Column>
          <Title>Attr</Title>
          <FuncString>[DC().GETFILEATTR{}]</FuncString>
          <Width>175</Width>
          <Align>0</Align>
          <Font>
            <Name>default</Name>
            <Size>10</Size>
            <Style>1</Style>
          </Font>
          <Overcolor>True</Overcolor>
          <TextColor>-2147483640</TextColor>
          <Background>-2147483643</Background>
          <Background2>-2147483643</Background2>
          <MarkColor>255</MarkColor>
          <CursorColor>-2147483635</CursorColor>
          <CursorText>-2147483634</CursorText>
        </Column>
      </Columns>
    </ColumnsSet>
  </ColumnsSets>
  <MainWindow>
    <Position>
      <Maximized>True</Maximized>
      <Splitter>50</Splitter>
    </Position>
  </MainWindow>
</doublecmd>
